{
  "North Vancouver District": {
    "place": {
      "name": "North Vancouver District",
      "state": "British Columbia",
      "country": "Canada",
      "type": "City/Government",
      "public": "public",
      "encoded": "north_vancouver_district",
      "consumer_base": 58120,
      "coord": [
        -123.0737925,
        49.3206294
      ]
    },
    "ratio": [
      {
        "status": "adopted",
        "org_credit_filter": [
          "Plant-Based Cities Movement"
        ],
        "org_credit_expanded": [
          "Plant-Based Cities Movement"
        ],
        "date": "2024"
      }
    ]
  }
}